Basic_Counter.v
module Basic_Counter #(parameter N = 3)(clk, rst, q);

input clk, rst;
output reg [N-1 : 0] q;

always @(posedge clk) begin
  if(rst) begin
    q <= 4'b000;
  end

  else if(q == 3'b111) begin
    q <= 3'b000;
  end

  else begin
    q <= q+1;
  end
end

endmodule

Basic_Counter_tb.v
module Basic_Counter_tb();

parameter N = 3;

reg clk, rst;
wire [N-1 : 0] q;

Basic_Counter #(.N(N)) dut (
    .clk(clk), 
    .rst(rst),
    .q(q)
);

initial begin
    $dumpfile("Basic_Counter_tb_Simulation.vcd");
    $dumpvars(0);
end

initial begin
  rst = 1'b1;
  clk = 1'b1;
  #50 rst = 1'b0;
  #1000 $finish();
end

always #10 clk = ~clk;

endmodule

Basic_Counter_tb_Simulation.vcd
$date
	Tue Mar 11 01:51:18 2025
$end
$version
	Icarus Verilog
$end
$timescale
	1s
$end
$scope module Basic_Counter_tb $end
$var wire 3 ! q [2:0] $end
$var parameter 32 " N $end
$var reg 1 # clk $end
$var reg 1 $ rst $end
$scope module dut $end
$var wire 1 # clk $end
$var wire 1 $ rst $end
$var parameter 32 % N $end
$var reg 3 & q [2:0] $end
$upscope $end
$upscope $end
$enddefinitions $end
$comment Show the parameter values. $end
$dumpall
b11 %
b11 "
$end
#0
$dumpvars
b0 &
1$
1#
b0 !
$end
#10
0#
#20
1#
#30
0#
#40
1#
#50
0#
0$
#60
b1 !
b1 &
1#
#70
0#
#80
b10 !
b10 &
1#
#90
0#
#100
b11 !
b11 &
1#
#110
0#
#120
b100 !
b100 &
1#
#130
0#
#140
b101 !
b101 &
1#
#150
0#
#160
b110 !
b110 &
1#
#170
0#
#180
b111 !
b111 &
1#
#190
0#
#200
b0 !
b0 &
1#
#210
0#
#220
b1 !
b1 &
1#
#230
0#
#240
b10 !
b10 &
1#
#250
0#
#260
b11 !
b11 &
1#
#270
0#
#280
b100 !
b100 &
1#
#290
0#
#300
b101 !
b101 &
1#
#310
0#
#320
b110 !
b110 &
1#
#330
0#
#340
b111 !
b111 &
1#
#350
0#
#360
b0 !
b0 &
1#
#370
0#
#380
b1 !
b1 &
1#
#390
0#
#400
b10 !
b10 &
1#
#410
0#
#420
b11 !
b11 &
1#
#430
0#
#440
b100 !
b100 &
1#
#450
0#
#460
b101 !
b101 &
1#
#470
0#
#480
b110 !
b110 &
1#
#490
0#
#500
b111 !
b111 &
1#
#510
0#
#520
b0 !
b0 &
1#
#530
0#
#540
b1 !
b1 &
1#
#550
0#
#560
b10 !
b10 &
1#
#570
0#
#580
b11 !
b11 &
1#
#590
0#
#600
b100 !
b100 &
1#
#610
0#
#620
b101 !
b101 &
1#
#630
0#
#640
b110 !
b110 &
1#
#650
0#
#660
b111 !
b111 &
1#
#670
0#
#680
b0 !
b0 &
1#
#690
0#
#700
b1 !
b1 &
1#
#710
0#
#720
b10 !
b10 &
1#
#730
0#
#740
b11 !
b11 &
1#
#750
0#
#760
b100 !
b100 &
1#
#770
0#
#780
b101 !
b101 &
1#
#790
0#
#800
b110 !
b110 &
1#
#810
0#
#820
b111 !
b111 &
1#
#830
0#
#840
b0 !
b0 &
1#
#850
0#
#860
b1 !
b1 &
1#
#870
0#
#880
b10 !
b10 &
1#
#890
0#
#900
b11 !
b11 &
1#
#910
0#
#920
b100 !
b100 &
1#
#930
0#
#940
b101 !
b101 &
1#
#950
0#
#960
b110 !
b110 &
1#
#970
0#
#980
b111 !
b111 &
1#
#990
0#
#1000
b0 !
b0 &
1#
#1010
0#
#1020
b1 !
b1 &
1#
#1030
0#
#1040
b10 !
b10 &
1#
